{
    "news": [
        {
            "header": "Release of the 3.0 Launcher",
            "body": "The new 3.0 Launcher is out! Make sure to grab the latest launcher"
        },
        {
            "header": "New Mod Config Options",
            "body": "Use the mod config page to modify and create your own mods! Save your changes to a custom config and apply after any official update."
        },
        {
            "header": "Back To Banoi Released!",
            "body": "This is a first pass on bringing IALR to the Dead Island Definitive game, lots more coming soon with the Unofficial Dev Tools"
        }
    ]
}